{
	"credit": "Made by JTK222",
	"textures": {
		"particle": "drpmedieval:blocks/wall_brazier/metal",
		"metal": "drpmedieval:blocks/wall_brazier/metal"
	},
	"elements": [
		{
			"from": [6.3431, 5.77609, 12.8431],
			"to": [9.6568, 6.32253, 16],
			"faces": {
				"up": {"uv": [6.3431, 12.8431, 9.6568, 16], "texture": "#metal"},
				"down": {"uv": [6.3431, 0, 9.6568, 3.1569], "texture": "#metal"}
			}
		},
		{
			"from": [6.34315, 6.12964, 12.72448],
			"to": [7.34315, 8.12964, 13.22448],
			"rotation": {"angle": -45, "axis": "x", "origin": [6.84315, 6.12964, 13.22448]},
			"faces": {
				"north": {"uv": [8.65685, 7.87036, 9.65685, 9.87036], "texture": "#metal"},
				"east": {"uv": [2.77552, 7.87036, 3.27552, 9.87036], "texture": "#metal"},
				"south": {"uv": [6.34315, 7.87036, 7.34315, 9.87036], "texture": "#metal"},
				"west": {"uv": [12.72448, 7.87036, 13.22448, 9.87036], "texture": "#metal"}
			}
		},
		{
			"from": [6.34315, 7.19082, 10.95932],
			"to": [7.34315, 9.69082, 11.45932],
			"rotation": {"angle": -22.5, "axis": "x", "origin": [6.84315, 8.44082, 11.20932]},
			"faces": {
				"north": {"uv": [8.65685, 6.30918, 9.65685, 8.80918], "texture": "#metal"},
				"east": {"uv": [4.54068, 6.30918, 5.04068, 8.80918], "texture": "#metal"},
				"south": {"uv": [6.34315, 6.30918, 7.34315, 8.80918], "texture": "#metal"},
				"west": {"uv": [10.95932, 6.30918, 11.45932, 8.80918], "texture": "#metal"}
			}
		},
		{
			"from": [8.65685, 7.19082, 10.95932],
			"to": [9.65685, 9.69082, 11.45932],
			"rotation": {"angle": -22.5, "axis": "x", "origin": [9.15685, 8.44082, 11.20932]},
			"faces": {
				"north": {"uv": [6.34315, 6.30918, 7.34315, 8.80918], "texture": "#metal"},
				"east": {"uv": [4.54068, 6.30918, 5.04068, 8.80918], "texture": "#metal"},
				"south": {"uv": [8.65685, 6.30918, 9.65685, 8.80918], "texture": "#metal"},
				"west": {"uv": [10.95932, 6.30918, 11.45932, 8.80918], "texture": "#metal"}
			}
		},
		{
			"from": [8.65685, 6.12964, 12.72448],
			"to": [9.65685, 8.12964, 13.22448],
			"rotation": {"angle": -45, "axis": "x", "origin": [9.15685, 6.12964, 13.22448]},
			"faces": {
				"north": {"uv": [6.34315, 7.87036, 7.34315, 9.87036], "texture": "#metal"},
				"east": {"uv": [2.77552, 7.87036, 3.27552, 9.87036], "texture": "#metal"},
				"south": {"uv": [8.65685, 7.87036, 9.65685, 9.87036], "texture": "#metal"},
				"west": {"uv": [12.72448, 7.87036, 13.22448, 9.87036], "texture": "#metal"}
			}
		},
		{
			"from": [9.27552, 6.12964, 12.8431],
			"to": [9.77552, 8.12964, 13.84315],
			"rotation": {"angle": -45, "axis": "z", "origin": [9.27552, 6.12964, 13.34315]},
			"faces": {
				"north": {"uv": [6.22448, 7.87036, 6.72448, 9.87036], "texture": "#metal"},
				"east": {"uv": [2.15685, 7.87036, 3.1569, 9.87036], "texture": "#metal"},
				"south": {"uv": [9.27552, 7.87036, 9.77552, 9.87036], "texture": "#metal"},
				"west": {"uv": [12.8431, 7.87036, 13.84315, 9.87036], "texture": "#metal"}
			}
		},
		{
			"from": [11.04068, 7.19082, 12.84315],
			"to": [11.54068, 9.69082, 13.84315],
			"rotation": {"angle": -22.5, "axis": "z", "origin": [11.29068, 8.44082, 13.34315]},
			"faces": {
				"north": {"uv": [4.45932, 6.30918, 4.95932, 8.80918], "texture": "#metal"},
				"east": {"uv": [2.15685, 6.30918, 3.15685, 8.80918], "texture": "#metal"},
				"south": {"uv": [11.04068, 6.30918, 11.54068, 8.80918], "texture": "#metal"},
				"west": {"uv": [12.84315, 6.30918, 13.84315, 8.80918], "texture": "#metal"}
			}
		},
		{
			"from": [11.04068, 7.19082, 15.09315],
			"to": [11.54068, 9.69082, 16],
			"rotation": {"angle": -22.5, "axis": "z", "origin": [11.29068, 8.44082, 15.59315]},
			"faces": {
				"north": {"uv": [4.45932, 6.30918, 4.95932, 8.80918], "texture": "#metal"},
				"east": {"uv": [0, 6.30918, 0.90685, 8.80918], "texture": "#metal"},
				"west": {"uv": [15.09315, 6.30918, 16, 8.80918], "texture": "#metal"}
			}
		},
		{
			"from": [9.27552, 6.12964, 15.09315],
			"to": [9.77552, 8.12964, 16],
			"rotation": {"angle": -45, "axis": "z", "origin": [9.27552, 6.12964, 15.59315]},
			"faces": {
				"north": {"uv": [6.22448, 7.87036, 6.72448, 9.87036], "texture": "#metal"},
				"east": {"uv": [0, 7.87036, 0.90685, 9.87036], "texture": "#metal"},
				"west": {"uv": [15.09315, 7.87036, 16, 9.87036], "texture": "#metal"}
			}
		},
		{
			"from": [6.34315, 6.02504, 13.11935],
			"to": [7.34315, 6.52504, 14.36935],
			"rotation": {"angle": 22.5, "axis": "x", "origin": [6.84315, 6.52504, 12.36935]},
			"faces": {
				"east": {"uv": [1.63065, 9.47496, 2.88065, 9.97496], "rotation": 90, "texture": "#metal"},
				"west": {"uv": [13.11935, 9.47496, 14.36935, 9.97496], "rotation": 270, "texture": "#metal"},
				"down": {"uv": [6.34315, 1.63065, 7.34315, 2.88065], "rotation": 180, "texture": "#metal"}
			}
		},
		{
			"from": [6.3431, 5.29773, 14.02577],
			"to": [7.34315, 5.77609, 16],
			"faces": {
				"east": {"uv": [0, 10.22391, 1.97423, 10.70227], "rotation": 90, "texture": "#metal"},
				"west": {"uv": [14.02577, 10.22391, 16, 10.70227], "rotation": 270, "texture": "#metal"},
				"down": {"uv": [6.3431, 0, 7.34315, 1.97423], "rotation": 180, "texture": "#metal"}
			}
		},
		{
			"from": [8.65685, 6.12071, 13.13838],
			"to": [9.65685, 6.62071, 14.13838],
			"rotation": {"angle": 22.5, "axis": "x", "origin": [9.15685, 6.62071, 12.13838]},
			"faces": {
				"east": {"uv": [1.86162, 9.37929, 2.86162, 9.87929], "rotation": 90, "texture": "#metal"},
				"west": {"uv": [13.13838, 9.37929, 14.13838, 9.87929], "rotation": 270, "texture": "#metal"},
				"down": {"uv": [8.65685, 1.86162, 9.65685, 2.86162], "rotation": 180, "texture": "#metal"}
			}
		},
		{
			"from": [8.65685, 5.3934, 13.7948],
			"to": [9.6568, 5.77609, 16],
			"faces": {
				"east": {"uv": [0, 10.22391, 2.2052, 10.6066], "rotation": 90, "texture": "#metal"},
				"west": {"uv": [13.7948, 10.22391, 16, 10.6066], "rotation": 270, "texture": "#metal"},
				"down": {"uv": [8.65685, 0, 9.6568, 2.2052], "rotation": 180, "texture": "#metal"}
			}
		},
		{
			"from": [6.22448, 6.12964, 15.09315],
			"to": [6.72448, 8.12964, 16],
			"rotation": {"angle": 45, "axis": "z", "origin": [6.72448, 6.12964, 15.59315]},
			"faces": {
				"north": {"uv": [9.27552, 7.87036, 9.77552, 9.87036], "texture": "#metal"},
				"east": {"uv": [0, 7.87036, 0.90685, 9.87036], "texture": "#metal"},
				"west": {"uv": [15.09315, 7.87036, 16, 9.87036], "texture": "#metal"}
			}
		},
		{
			"from": [6.22448, 6.12964, 12.8431],
			"to": [6.72448, 8.12964, 13.84315],
			"rotation": {"angle": 45, "axis": "z", "origin": [6.72448, 6.12964, 13.34315]},
			"faces": {
				"north": {"uv": [9.27552, 7.87036, 9.77552, 9.87036], "texture": "#metal"},
				"east": {"uv": [2.15685, 7.87036, 3.1569, 9.87036], "texture": "#metal"},
				"south": {"uv": [6.22448, 7.87036, 6.72448, 9.87036], "texture": "#metal"},
				"west": {"uv": [12.8431, 7.87036, 13.84315, 9.87036], "texture": "#metal"}
			}
		},
		{
			"from": [4.45932, 7.19082, 12.84315],
			"to": [4.95932, 9.69082, 13.84315],
			"rotation": {"angle": 22.5, "axis": "z", "origin": [4.70932, 8.44082, 13.34315]},
			"faces": {
				"north": {"uv": [11.04068, 6.30918, 11.54068, 8.80918], "texture": "#metal"},
				"east": {"uv": [2.15685, 6.30918, 3.15685, 8.80918], "texture": "#metal"},
				"south": {"uv": [4.45932, 6.30918, 4.95932, 8.80918], "texture": "#metal"},
				"west": {"uv": [12.84315, 6.30918, 13.84315, 8.80918], "texture": "#metal"}
			}
		},
		{
			"from": [4.45932, 7.19082, 15.09315],
			"to": [4.95932, 9.69082, 16],
			"rotation": {"angle": 22.5, "axis": "z", "origin": [4.70932, 8.44082, 15.59315]},
			"faces": {
				"north": {"uv": [11.04068, 6.30918, 11.54068, 8.80918], "texture": "#metal"},
				"east": {"uv": [0, 6.30918, 0.90685, 8.80918], "texture": "#metal"},
				"west": {"uv": [15.09315, 6.30918, 16, 8.80918], "texture": "#metal"}
			}
		},
		{
			"from": [6.22448, 6.12964, 13.8431],
			"to": [6.72448, 7.37964, 15.09315],
			"rotation": {"angle": 45, "axis": "z", "origin": [6.72448, 6.12964, 13.34315]},
			"faces": {
				"east": {"uv": [0.90685, 8.62036, 2.1569, 9.87036], "texture": "#metal"},
				"west": {"uv": [13.8431, 8.62036, 15.09315, 9.87036], "texture": "#metal"},
				"up": {"uv": [6.22448, 13.8431, 6.72448, 15.09315], "rotation": 90, "texture": "#metal"}
			}
		},
		{
			"from": [7.34315, 6.12964, 12.72448],
			"to": [8.65685, 7.37964, 13.22448],
			"rotation": {"angle": -45, "axis": "x", "origin": [9.15685, 6.12964, 13.22448]},
			"faces": {
				"north": {"uv": [7.34315, 8.62036, 8.65685, 9.87036], "texture": "#metal"},
				"south": {"uv": [7.34315, 8.62036, 8.65685, 9.87036], "texture": "#metal"},
				"up": {"uv": [7.34315, 12.72448, 8.65685, 13.22448], "texture": "#metal"}
			}
		},
		{
			"from": [9.27552, 6.12964, 13.84315],
			"to": [9.77552, 7.37964, 15.09315],
			"rotation": {"angle": -45, "axis": "z", "origin": [9.27552, 6.12964, 15.59315]},
			"faces": {
				"east": {"uv": [0.90685, 8.62036, 2.15685, 9.87036], "texture": "#metal"},
				"west": {"uv": [13.84315, 8.62036, 15.09315, 9.87036], "texture": "#metal"},
				"up": {"uv": [9.27552, 13.84315, 9.77552, 15.09315], "rotation": 90, "texture": "#metal"}
			}
		},
		{
			"name": "octagon",
			"from": [6.34315, 9.5, 10.5],
			"to": [9.65685, 10.5, 11],
			"rotation": {"angle": 45, "axis": "y", "origin": [8, 10, 14.5]},
			"faces": {
				"north": {"uv": [6.34315, 5.5, 9.65685, 6.5], "texture": "#metal"},
				"east": {"uv": [5, 5.5, 5.5, 6.5], "texture": "#metal"},
				"south": {"uv": [6.34315, 5.5, 9.65685, 6.5], "texture": "#metal"},
				"west": {"uv": [10.5, 5.5, 11, 6.5], "texture": "#metal"},
				"up": {"uv": [6.34315, 10.5, 9.65685, 11], "texture": "#metal"},
				"down": {"uv": [6.34315, 5, 9.65685, 5.5], "texture": "#metal"}
			}
		},
		{
			"name": "octagon",
			"from": [6.3431, 9.5, 10.5],
			"to": [9.6568, 10.5, 11],
			"faces": {
				"north": {"uv": [6.3432, 5.5, 9.6569, 6.5], "texture": "#metal"},
				"east": {"uv": [5, 5.5, 5.5, 6.5], "texture": "#metal"},
				"south": {"uv": [6.3431, 5.5, 9.6568, 6.5], "texture": "#metal"},
				"west": {"uv": [10.5, 5.5, 11, 6.5], "texture": "#metal"},
				"up": {"uv": [6.3431, 10.5, 9.6568, 11], "texture": "#metal"},
				"down": {"uv": [6.3431, 5, 9.6568, 5.5], "texture": "#metal"}
			}
		},
		{
			"name": "octagon",
			"from": [4, 9.5, 12.84315],
			"to": [4.5, 10.5, 16],
			"faces": {
				"north": {"uv": [11.5, 5.5, 12, 6.5], "texture": "#metal"},
				"east": {"uv": [0, 5.5, 3.15685, 6.5], "texture": "#metal"},
				"west": {"uv": [12.84315, 5.5, 16, 6.5], "texture": "#metal"},
				"up": {"uv": [4, 12.84315, 4.5, 16], "texture": "#metal"},
				"down": {"uv": [4, 0, 4.5, 3.15685], "texture": "#metal"}
			}
		},
		{
			"name": "octagon",
			"from": [11.5, 9.5, 12.84315],
			"to": [12, 10.5, 16.15685],
			"rotation": {"angle": 45, "axis": "y", "origin": [8, 10, 14.5]},
			"faces": {
				"north": {"uv": [4, 5.5, 4.5, 6.5], "texture": "#metal"},
				"east": {"uv": [0, 5.5, 3.15685, 6.5], "texture": "#metal"},
				"south": {"uv": [11.5, 5.5, 12, 6.5], "texture": "#metal"},
				"west": {"uv": [12.84315, 5.5, 16, 6.5], "texture": "#metal"},
				"up": {"uv": [11.5, 12.84315, 12, 16], "texture": "#metal"},
				"down": {"uv": [11.5, 0, 12, 3.15685], "texture": "#metal"}
			}
		},
		{
			"name": "octagon",
			"from": [11.5, 9.5, 12.84315],
			"to": [12, 10.5, 16.00005],
			"faces": {
				"north": {"uv": [4, 5.5, 4.5, 6.5], "texture": "#metal"},
				"east": {"uv": [0, 5.5, 3.15685, 6.5], "texture": "#metal"},
				"west": {"uv": [12.84315, 5.5, 16, 6.5], "texture": "#metal"},
				"up": {"uv": [11.5, 12.84315, 12, 16], "texture": "#metal"},
				"down": {"uv": [11.5, 0, 12, 3.15685], "texture": "#metal"}
			}
		}
	],
	"groups": [
		{
			"name": "firebowl",
			"children": [0, 1, 2, 3, 4, 5, 6, 7, 8, 9, 10, 11, 12, 13, 14, 15, 16, 17, 18, 19,
				{
					"name": "octagon",
					"children": [20, 21, 22, 23, 24]
				}
			]
		}
	]
}